odoo10_addon_quality_control_formula-10.0.1.0.0.99.dev4-py3.8-nspkg.pth
odoo/addons/quality_control_formula/README.rst
odoo/addons/quality_control_formula/__init__.py
odoo/addons/quality_control_formula/__manifest__.py
odoo/addons/quality_control_formula/i18n/it.po
odoo/addons/quality_control_formula/i18n/quality_control_formula.pot
odoo/addons/quality_control_formula/models/__init__.py
odoo/addons/quality_control_formula/models/qc_inspection.py
odoo/addons/quality_control_formula/models/qc_inspection_line.py
odoo/addons/quality_control_formula/models/qc_test_question.py
odoo/addons/quality_control_formula/readme/DESCRIPTION.rst
odoo/addons/quality_control_formula/readme/USAGE.rst
odoo/addons/quality_control_formula/static/description/icon.png
odoo/addons/quality_control_formula/static/description/index.html
odoo/addons/quality_control_formula/tests/__init__.py
odoo/addons/quality_control_formula/tests/test_quality_control_formula.py
odoo/addons/quality_control_formula/views/qc_inspection_line_views.xml
odoo/addons/quality_control_formula/views/qc_inspection_views.xml
odoo/addons/quality_control_formula/views/qc_test_question_views.xml
odoo/addons/quality_control_formula/views/qc_test_views.xml
odoo10_addon_quality_control_formula-10.0.1.0.0.99.dev4.dist-info/METADATA
odoo10_addon_quality_control_formula-10.0.1.0.0.99.dev4.dist-info/WHEEL
odoo10_addon_quality_control_formula-10.0.1.0.0.99.dev4.dist-info/namespace_packages.txt
odoo10_addon_quality_control_formula-10.0.1.0.0.99.dev4.dist-info/top_level.txt
odoo10_addon_quality_control_formula-10.0.1.0.0.99.dev4.dist-info/RECORD
