Metadata-Version: 2.1
Name: odoo10-addon-quality-control-formula
Version: 10.0.1.0.0.99.dev4
Summary: Use formulas in inspection lines.
Home-page: https://github.com/OCA/manufacture/tree/10.0/quality_control_formula
Author: Agile Business Group, Odoo Community Association (OCA)
Author-email: support@odoo-community.org
License: AGPL-3
Platform: UNKNOWN
Classifier: Programming Language :: Python
Classifier: Framework :: Odoo
Classifier: Framework :: Odoo :: 10.0
Classifier: License :: OSI Approved :: GNU Affero General Public License v3
Classifier: Development Status :: 4 - Beta
Requires-Python: ~=2.7
Requires-Dist: odoo10-addon-quality-control
Requires-Dist: odoo <10.1dev,>=10.0
